{
  "kind": "drive#fileList",
  "incompleteSearch": false,
  "files": [
    {
      "kind": "drive#file",
      "id": "10orhTPfOE7DfrcGMxEwDvV0IHz6lZsKF",
      "name": "wünschen : Wunsch.mp4",
      "mimeType": "video/mp4"
    },
    {
      "kind": "drive#file",
      "id": "1kF7g4CIqr61CJoFH9lHD9nINvPGKS1fS",
      "name": "folgen.mp4",
      "mimeType": "video/mp4"
    },
    {
      "kind": "drive#file",
      "id": "12LwSPLAVhFioEUm5wWai130-qLNYT3Lq",
      "name": "wünschen.mp4",
      "mimeType": "video/mp4"
    },
    {
      "kind": "drive#file",
      "id": "1Rg4Ih7IMq3huQ5DcnZgrlIo4ed_m9Nx4",
      "name": "zwicken.mp4",
      "mimeType": "video/mp4"
    },
    {
      "kind": "drive#file",
      "id": "1ts0GLzOCeXNYHIKzuxqoY7X58qA82Nm7",
      "name": "zeigen.mp4",
      "mimeType": "video/mp4"
    },
    {
      "kind": "drive#file",
      "id": "1Hi5OmSGhxv6lEWLodlYhHzW1yXprbVAS",
      "name": "wütend : zornig sein.mp4",
      "mimeType": "video/mp4"
    },
    {
      "kind": "drive#file",
      "id": "1f5z0lSzPZrTgRPCZ8_qowMP1Bd70ah1o",
      "name": "wünschen (2).mp4",
      "mimeType": "video/mp4"
    },
    {
      "kind": "drive#file",
      "id": "1VyKnK2brYOKc4oKYPDSHjWTi45Fp9Mpe",
      "name": "wünschen (1).mp4",
      "mimeType": "video/mp4"
    },
    {
      "kind": "drive#file",
      "id": "1bujpnkfL_5ItwJDg2XEmqi4zW0XGVgUo",
      "name": "wegnehmen.mp4",
      "mimeType": "video/mp4"
    },
    {
      "kind": "drive#file",
      "id": "1rN46Y0cK1PwXBY6dC7-0Jx3ix0B0Mb4H",
      "name": "verstecken.mp4",
      "mimeType": "video/mp4"
    },
    {
      "kind": "drive#file",
      "id": "1LUHMwmLnXvNM_AMf9lKCYpch2VwpNbio",
      "name": "verfolgen.mp4",
      "mimeType": "video/mp4"
    },
    {
      "kind": "drive#file",
      "id": "1VmhN6VmErZTvTSffHd8jfaDIc18pPkvs",
      "name": "treffen : begegnen.mp4",
      "mimeType": "video/mp4"
    },
    {
      "kind": "drive#file",
      "id": "13ky5DaL7lr6dfohvTMsX9SRB2AJHWOrR",
      "name": "schlagen.mp4",
      "mimeType": "video/mp4"
    },
    {
      "kind": "drive#file",
      "id": "1iZG6SNk89KEB5oPHssoOJPpFBUUmOx8I",
      "name": "pusten.mp4",
      "mimeType": "video/mp4"
    },
    {
      "kind": "drive#file",
      "id": "1C41Wk9Cdzr0EzjSnPfvHnYeaAQqR_VPb",
      "name": "klopfen.mp4",
      "mimeType": "video/mp4"
    },
    {
      "kind": "drive#file",
      "id": "1yZJXwEvrSUmbtDdYG8lW6BS5SjpR6WPH",
      "name": "Haare ziehen.mp4",
      "mimeType": "video/mp4"
    },
    {
      "kind": "drive#file",
      "id": "1dNqfLGMbdpQRg51kCkbCr729Bhk3r1o0",
      "name": "fragen (du mich).mp4",
      "mimeType": "video/mp4"
    },
    {
      "kind": "drive#file",
      "id": "1T35ym8EyWVTBfNpZRMIGjwUOe3nesQKj",
      "name": "fragen (ich euch).mp4",
      "mimeType": "video/mp4"
    },
    {
      "kind": "drive#file",
      "id": "1h9r0OumQuNu5xwWCh9BY2bxr_q7SH7AC",
      "name": "fragen (ich dich).mp4",
      "mimeType": "video/mp4"
    },
    {
      "kind": "drive#file",
      "id": "1HEDwxRDpc7hqVwd2CY7XRhtx2sUtXjGY",
      "name": "anfassen.mp4",
      "mimeType": "video/mp4"
    },
    {
      "kind": "drive#file",
      "id": "1yFBKjQLUvudbGjjvglmqPixwdffcuC-v",
      "name": "berühren.mp4",
      "mimeType": "video/mp4"
    }
  ]
}
